{
  "$schema": "https://raw.githubusercontent.com/spdx/spdx-spec/v2.2.1/schemas/spdx-schema.json",
  "spdxVersion": "SPDX-2.2",
  "dataLicense": "CC0-1.0",
  "SPDXID": "SPDXRef-DOCUMENT",
  "documentNamespace": "https://spdx.org/spdxdocs/re2-x64-windows-2025-11-05-5e5428ac-f29a-4e92-a871-3a3a867d9e0d",
  "name": "re2:x64-windows@2025-11-05 8752c45e5e51c16602549419e2ca15d56cce2178734778d7d770817c0c163b11",
  "creationInfo": {
    "creators": [
      "Tool: vcpkg-2025-12-16-44bb3ce006467fc13ba37ca099f64077b8bbf84d"
    ],
    "created": "2026-07-12T16:38:33Z"
  },
  "relationships": [
    {
      "spdxElementId": "SPDXRef-port",
      "relationshipType": "GENERATES",
      "relatedSpdxElement": "SPDXRef-binary"
    },
    {
      "spdxElementId": "SPDXRef-port",
      "relationshipType": "CONTAINS",
      "relatedSpdxElement": "SPDXRef-port-file-0"
    },
    {
      "spdxElementId": "SPDXRef-port",
      "relationshipType": "CONTAINS",
      "relatedSpdxElement": "SPDXRef-port-file-1"
    },
    {
      "spdxElementId": "SPDXRef-port-file-1",
      "relationshipType": "DEPENDENCY_MANIFEST_OF",
      "relatedSpdxElement": "SPDXRef-port"
    },
    {
      "spdxElementId": "SPDXRef-binary",
      "relationshipType": "CONTAINS",
      "relatedSpdxElement": "SPDXRef-binary-file-0"
    },
    {
      "spdxElementId": "SPDXRef-binary",
      "relationshipType": "CONTAINS",
      "relatedSpdxElement": "SPDXRef-binary-file-1"
    },
    {
      "spdxElementId": "SPDXRef-binary",
      "relationshipType": "CONTAINS",
      "relatedSpdxElement": "SPDXRef-binary-file-2"
    },
    {
      "spdxElementId": "SPDXRef-binary",
      "relationshipType": "CONTAINS",
      "relatedSpdxElement": "SPDXRef-binary-file-3"
    },
    {
      "spdxElementId": "SPDXRef-binary",
      "relationshipType": "CONTAINS",
      "relatedSpdxElement": "SPDXRef-binary-file-4"
    },
    {
      "spdxElementId": "SPDXRef-binary",
      "relationshipType": "CONTAINS",
      "relatedSpdxElement": "SPDXRef-binary-file-5"
    },
    {
      "spdxElementId": "SPDXRef-binary",
      "relationshipType": "CONTAINS",
      "relatedSpdxElement": "SPDXRef-binary-file-6"
    },
    {
      "spdxElementId": "SPDXRef-binary",
      "relationshipType": "CONTAINS",
      "relatedSpdxElement": "SPDXRef-binary-file-7"
    },
    {
      "spdxElementId": "SPDXRef-binary",
      "relationshipType": "CONTAINS",
      "relatedSpdxElement": "SPDXRef-binary-file-8"
    },
    {
      "spdxElementId": "SPDXRef-binary",
      "relationshipType": "CONTAINS",
      "relatedSpdxElement": "SPDXRef-binary-file-9"
    },
    {
      "spdxElementId": "SPDXRef-binary",
      "relationshipType": "CONTAINS",
      "relatedSpdxElement": "SPDXRef-binary-file-10"
    },
    {
      "spdxElementId": "SPDXRef-binary",
      "relationshipType": "CONTAINS",
      "relatedSpdxElement": "SPDXRef-binary-file-11"
    },
    {
      "spdxElementId": "SPDXRef-binary",
      "relationshipType": "CONTAINS",
      "relatedSpdxElement": "SPDXRef-binary-file-12"
    },
    {
      "spdxElementId": "SPDXRef-binary",
      "relationshipType": "CONTAINS",
      "relatedSpdxElement": "SPDXRef-binary-file-13"
    },
    {
      "spdxElementId": "SPDXRef-binary",
      "relationshipType": "CONTAINS",
      "relatedSpdxElement": "SPDXRef-binary-file-14"
    },
    {
      "spdxElementId": "SPDXRef-binary",
      "relationshipType": "CONTAINS",
      "relatedSpdxElement": "SPDXRef-binary-file-15"
    },
    {
      "spdxElementId": "SPDXRef-binary",
      "relationshipType": "CONTAINS",
      "relatedSpdxElement": "SPDXRef-binary-file-16"
    },
    {
      "spdxElementId": "SPDXRef-binary",
      "relationshipType": "CONTAINS",
      "relatedSpdxElement": "SPDXRef-binary-file-17"
    },
    {
      "spdxElementId": "SPDXRef-binary",
      "relationshipType": "CONTAINS",
      "relatedSpdxElement": "SPDXRef-binary-file-18"
    }
  ],
  "packages": [
    {
      "name": "re2",
      "SPDXID": "SPDXRef-port",
      "versionInfo": "2025-11-05",
      "downloadLocation": "git+https://github.com/Microsoft/vcpkg@cdb3c6b427f023ec6af6433f0494e2e7ec0f708f",
      "homepage": "https://github.com/google/re2",
      "licenseConcluded": "BSD-3-Clause",
      "licenseDeclared": "NOASSERTION",
      "copyrightText": "NOASSERTION",
      "description": "RE2 is a fast, safe, thread-friendly alternative to backtracking regular expression engines like those used in PCRE, Perl, and Python. It is a C++ library.",
      "comment": "This is the port (recipe) consumed by vcpkg."
    },
    {
      "name": "re2:x64-windows",
      "SPDXID": "SPDXRef-binary",
      "versionInfo": "8752c45e5e51c16602549419e2ca15d56cce2178734778d7d770817c0c163b11",
      "downloadLocation": "NONE",
      "licenseConcluded": "BSD-3-Clause",
      "licenseDeclared": "NOASSERTION",
      "copyrightText": "NOASSERTION",
      "comment": "This is a binary package built by vcpkg."
    },
    {
      "SPDXID": "SPDXRef-resource-0",
      "name": "google/re2",
      "downloadLocation": "git+https://github.com/google/re2@927f5d53caf8111721e734cf24724686bb745f55",
      "licenseConcluded": "NOASSERTION",
      "licenseDeclared": "NOASSERTION",
      "copyrightText": "NOASSERTION",
      "checksums": [
        {
          "algorithm": "SHA512",
          "checksumValue": "35103a46a6350084f2d09ccfcf4322dac7364c61fbdad8bfcbd41b39990f83a260d2a8cd5ca019a3f24b71faf1588c7dabf07c3dddae5268bcc5b9502b87658a"
        }
      ]
    }
  ],
  "files": [
    {
      "fileName": "./portfile.cmake",
      "SPDXID": "SPDXRef-port-file-0",
      "checksums": [
        {
          "algorithm": "SHA256",
          "checksumValue": "b85f302d11f21ba7cedd228b4a96dff9dfa7317979047b62c9cfb2d329147de4"
        }
      ],
      "licenseConcluded": "NOASSERTION",
      "copyrightText": "NOASSERTION"
    },
    {
      "fileName": "./vcpkg.json",
      "SPDXID": "SPDXRef-port-file-1",
      "checksums": [
        {
          "algorithm": "SHA256",
          "checksumValue": "050234748a052b8f27341586826521cc34ebe5877985db1bbcd7fa568e577fcd"
        }
      ],
      "licenseConcluded": "NOASSERTION",
      "copyrightText": "NOASSERTION"
    },
    {
      "fileName": "./bin/re2.dll",
      "SPDXID": "SPDXRef-binary-file-0",
      "checksums": [
        {
          "algorithm": "SHA256",
          "checksumValue": "e4020c9865b452fbc5c0999c418f0d4a4232460b363a44d33698b6b8ac237af0"
        }
      ],
      "licenseConcluded": "NOASSERTION",
      "copyrightText": "NOASSERTION"
    },
    {
      "fileName": "./bin/re2.pdb",
      "SPDXID": "SPDXRef-binary-file-1",
      "checksums": [
        {
          "algorithm": "SHA256",
          "checksumValue": "5e1c74c2e92ab6d1204675cc01f67f1fdb957ca08bdc39761c3d169ffaae9aa3"
        }
      ],
      "licenseConcluded": "NOASSERTION",
      "copyrightText": "NOASSERTION"
    },
    {
      "fileName": "./BUILD_INFO",
      "SPDXID": "SPDXRef-binary-file-2",
      "checksums": [
        {
          "algorithm": "SHA256",
          "checksumValue": "5e7f821ab4eb804deb535baa7b41edca682d0303cf21a91908c98d5c9a7dcf4d"
        }
      ],
      "licenseConcluded": "NOASSERTION",
      "copyrightText": "NOASSERTION"
    },
    {
      "fileName": "./debug/bin/re2.dll",
      "SPDXID": "SPDXRef-binary-file-3",
      "checksums": [
        {
          "algorithm": "SHA256",
          "checksumValue": "32f3af1a569de7d01fcac6423f9ec95590711e87971602953ea4ee7f9c6345c4"
        }
      ],
      "licenseConcluded": "NOASSERTION",
      "copyrightText": "NOASSERTION"
    },
    {
      "fileName": "./debug/bin/re2.pdb",
      "SPDXID": "SPDXRef-binary-file-4",
      "checksums": [
        {
          "algorithm": "SHA256",
          "checksumValue": "777c62c586ab4e2bc7430222548dd3acfc72fb4b65e271dd2cef587088b8bd08"
        }
      ],
      "licenseConcluded": "NOASSERTION",
      "copyrightText": "NOASSERTION"
    },
    {
      "fileName": "./debug/lib/pkgconfig/re2.pc",
      "SPDXID": "SPDXRef-binary-file-5",
      "checksums": [
        {
          "algorithm": "SHA256",
          "checksumValue": "d40105c48c2f2763ef0321a9bd82c31f40d61f57f6d2e9ecb01b0265dd33fef4"
        }
      ],
      "licenseConcluded": "NOASSERTION",
      "copyrightText": "NOASSERTION"
    },
    {
      "fileName": "./debug/lib/re2.lib",
      "SPDXID": "SPDXRef-binary-file-6",
      "checksums": [
        {
          "algorithm": "SHA256",
          "checksumValue": "58143224ff5fdc2ed71958f22b48e2f167d7d60cfb08d7ffd4e51aab3a865f7d"
        }
      ],
      "licenseConcluded": "NOASSERTION",
      "copyrightText": "NOASSERTION"
    },
    {
      "fileName": "./include/re2/filtered_re2.h",
      "SPDXID": "SPDXRef-binary-file-7",
      "checksums": [
        {
          "algorithm": "SHA256",
          "checksumValue": "1ea210499ecb637cd0c8ebc5f20d0c3be02697e4aa0f614ebc831812709227f5"
        }
      ],
      "licenseConcluded": "NOASSERTION",
      "copyrightText": "NOASSERTION"
    },
    {
      "fileName": "./include/re2/re2.h",
      "SPDXID": "SPDXRef-binary-file-8",
      "checksums": [
        {
          "algorithm": "SHA256",
          "checksumValue": "59f4d4b5318fcb6acf0c90f17d17e71903a87ec25d75fcf5d13e738beb29490f"
        }
      ],
      "licenseConcluded": "NOASSERTION",
      "copyrightText": "NOASSERTION"
    },
    {
      "fileName": "./include/re2/set.h",
      "SPDXID": "SPDXRef-binary-file-9",
      "checksums": [
        {
          "algorithm": "SHA256",
          "checksumValue": "d862a0e44570aad753ab7b68ec1c3e34a95075aaf95e50b208b26b894cefd903"
        }
      ],
      "licenseConcluded": "NOASSERTION",
      "copyrightText": "NOASSERTION"
    },
    {
      "fileName": "./include/re2/stringpiece.h",
      "SPDXID": "SPDXRef-binary-file-10",
      "checksums": [
        {
          "algorithm": "SHA256",
          "checksumValue": "59c1438095decbdab33a6140f6b358634e3dc31c36408ba9ce3b382ab3fb6c5a"
        }
      ],
      "licenseConcluded": "NOASSERTION",
      "copyrightText": "NOASSERTION"
    },
    {
      "fileName": "./lib/pkgconfig/re2.pc",
      "SPDXID": "SPDXRef-binary-file-11",
      "checksums": [
        {
          "algorithm": "SHA256",
          "checksumValue": "62b44e19f0510111b08105bb301792f42af99d21ae600f6a76c744a5376c3e45"
        }
      ],
      "licenseConcluded": "NOASSERTION",
      "copyrightText": "NOASSERTION"
    },
    {
      "fileName": "./lib/re2.lib",
      "SPDXID": "SPDXRef-binary-file-12",
      "checksums": [
        {
          "algorithm": "SHA256",
          "checksumValue": "c58181d6cde9323dc4a54904140bb1e9b22da4bd21dea7384b84d7aac53c8fe0"
        }
      ],
      "licenseConcluded": "NOASSERTION",
      "copyrightText": "NOASSERTION"
    },
    {
      "fileName": "./share/re2/copyright",
      "SPDXID": "SPDXRef-binary-file-13",
      "checksums": [
        {
          "algorithm": "SHA256",
          "checksumValue": "6040cda75d90b1738292a631d89934c411ef7ffd543c4d6a1b7edfc8edf29449"
        }
      ],
      "licenseConcluded": "NOASSERTION",
      "copyrightText": "NOASSERTION"
    },
    {
      "fileName": "./share/re2/re2Config.cmake",
      "SPDXID": "SPDXRef-binary-file-14",
      "checksums": [
        {
          "algorithm": "SHA256",
          "checksumValue": "cb84a8e21c98cef902cb0f1f3dbc2bc3ac986e3ebc36f2f7b931a38ee5de79ed"
        }
      ],
      "licenseConcluded": "NOASSERTION",
      "copyrightText": "NOASSERTION"
    },
    {
      "fileName": "./share/re2/re2ConfigVersion.cmake",
      "SPDXID": "SPDXRef-binary-file-15",
      "checksums": [
        {
          "algorithm": "SHA256",
          "checksumValue": "d50c63f6a3a9ee2669faa93bdefb262f1186c395b747c3b48007a14c63e8a215"
        }
      ],
      "licenseConcluded": "NOASSERTION",
      "copyrightText": "NOASSERTION"
    },
    {
      "fileName": "./share/re2/re2Targets-debug.cmake",
      "SPDXID": "SPDXRef-binary-file-16",
      "checksums": [
        {
          "algorithm": "SHA256",
          "checksumValue": "bb40eb4b360b8739e3d1bd45b4744a57a7d8539ed907191a80ae9671f0b9a62f"
        }
      ],
      "licenseConcluded": "NOASSERTION",
      "copyrightText": "NOASSERTION"
    },
    {
      "fileName": "./share/re2/re2Targets-release.cmake",
      "SPDXID": "SPDXRef-binary-file-17",
      "checksums": [
        {
          "algorithm": "SHA256",
          "checksumValue": "d8003bfbba3ca328dd553cb0777d3e9774b3cbb73d02e55f583bffa4a2b47a3b"
        }
      ],
      "licenseConcluded": "NOASSERTION",
      "copyrightText": "NOASSERTION"
    },
    {
      "fileName": "./share/re2/re2Targets.cmake",
      "SPDXID": "SPDXRef-binary-file-18",
      "checksums": [
        {
          "algorithm": "SHA256",
          "checksumValue": "a15cfbcccee66a50b3dd9bea3b644ccaef27847766a7e2933569c8014eb07ce3"
        }
      ],
      "licenseConcluded": "NOASSERTION",
      "copyrightText": "NOASSERTION"
    }
  ]
}
